{
  "title": "AOT no Requiem",
  "description": "Alternative ending to the Attack on Titan manga series adapting the Akatsuki no Requiem Theory.",
  "artist": "AOTNR Team",
  "author": "AOTNR Team",
  "cover": "https://i.imgur.com/OoaozoG.jpg",
  "chapters": {
    "1": {
      "title": "Part 1",
      "volume": "",
      "groups": {
        "AOTNR Team": "/proxy/api/imgur/chapter/aot-no-requiem-part-1-r54wRAP"
      },
      "last_updated": "1622340000"
    },
   "2": {
      "title": "Part 2",
      "volume": "",
      "groups": {
        "AOTNR Team": "/proxy/api/imgur/chapter/aot-no-requiem-part-2-4rN0Itu"
      },
      "last_updated": "1631158680"
    },
   "3": {
      "title": "Part 3",
      "volume": "",
      "groups": {
        "AOTNR Team": "/proxy/api/imgur/chapter/aot-no-requiem-part-3-CLzOK9Z"
      },
      "last_updated": "1659751800"
      }    
  }
}
